dj_raw_sql/__init__.py
dj_raw_sql/main.py
dj_raw_sql/py.typed
dj_raw_sql/types.py
dj_raw_sql-2.0.0.dist-info/LICENSE
dj_raw_sql-2.0.0.dist-info/WHEEL
dj_raw_sql-2.0.0.dist-info/METADATA
dj_raw_sql-2.0.0.dist-info/RECORD
