Metadata-Version: 2.1
Name: dj-raw-sql
Version: 2.0.0
Summary: This is a Django wrapper to make it easier to write raw SQL queries.
Home-page: https://github.com/axemanofic/dj-raw-sql
License: MIT
Keywords: python,django
Author: Roman Sotnikov
Author-email: axeman.ofic@gmail.com
Maintainer: Roman
Maintainer-email: axeman.ofic@gmail.com
Requires-Python: >=3.11,<4.0
Classifier: Development Status :: 5 - Production/Stable
Classifier: Framework :: Django :: 3.2
Classifier: License :: OSI Approved :: MIT License
Classifier: Programming Language :: Python :: 3
Classifier: Programming Language :: Python :: 3.11
Classifier: Programming Language :: Python :: 3.11
Requires-Dist: django (>=3.2)
Project-URL: Repository, https://github.com/axemanofic/dj-raw-sql
